lzid/__init__.py
lzid/lzid.py
lzid-0.2.0.dist-info/LICENSE
lzid-0.2.0.dist-info/METADATA
lzid-0.2.0.dist-info/WHEEL
lzid-0.2.0.dist-info/top_level.txt
lzid-0.2.0.dist-info/RECORD
